certbot_dns_anx/__init__.py
certbot_dns_anx/py.typed
certbot_dns_anx/_internal/__init__.py
certbot_dns_anx/_internal/dns_anx.py
certbot_dns_anx-2.0.0.dist-info/LICENCE
certbot_dns_anx-2.0.0.dist-info/METADATA
certbot_dns_anx-2.0.0.dist-info/WHEEL
certbot_dns_anx-2.0.0.dist-info/entry_points.txt
certbot_dns_anx-2.0.0.dist-info/top_level.txt
certbot_dns_anx-2.0.0.dist-info/RECORD
