Metadata-Version: 2.1
Name: certbot-dns-anx
Version: 2.0.0
Summary: ANX DNS authentication plugin for Certbot
Home-page: https://github.com/egeback/pycertbot-anx
Author: Marky Egebäck
Author-email: marky@egeback.se
License: Apache License 2.0
Classifier: Development Status :: 5 - Production/Stable
Classifier: Environment :: Plugins
Classifier: Intended Audience :: System Administrators
Classifier: License :: OSI Approved :: Apache Software License
Classifier: Operating System :: POSIX :: Linux
Classifier: Programming Language :: Python
Classifier: Programming Language :: Python :: 3
Classifier: Programming Language :: Python :: 3.8
Classifier: Programming Language :: Python :: 3.9
Classifier: Programming Language :: Python :: 3.10
Classifier: Programming Language :: Python :: 3.11
Classifier: Programming Language :: Python :: 3.12
Classifier: Topic :: Internet :: WWW/HTTP
Classifier: Topic :: Security
Classifier: Topic :: System :: Installation/Setup
Classifier: Topic :: System :: Networking
Classifier: Topic :: System :: Systems Administration
Classifier: Topic :: Utilities
Requires-Python: >=3.8
License-File: LICENCE
Requires-Dist: setuptools >=41.6.0
Requires-Dist: certbot >=2.8.0
Requires-Dist: pyanxdns >=0.2.5
Requires-Dist: acme >=2.0.0
Requires-Dist: certbot >=2.0.0
Provides-Extra: docs
Requires-Dist: Sphinx >=1.0 ; extra == 'docs'
Requires-Dist: sphinx-rtd-theme ; extra == 'docs'
Provides-Extra: test
Requires-Dist: pytest ; extra == 'test'
